contract_validator/__init__.py
contract_validator-0.1.3.dist-info/WHEEL
contract_validator-0.1.3.dist-info/METADATA
contract_validator-0.1.3.dist-info/RECORD
