Metadata-Version: 2.1
Name: contract-validator
Version: 0.1.3
Summary: Validador de contrato baseado no JsonSchema
Author: Victor Magdalene
Requires-Python: >=3.7,<4.0
Classifier: Programming Language :: Python :: 3
Classifier: Programming Language :: Python :: 3.7
Classifier: Programming Language :: Python :: 3.8
Classifier: Programming Language :: Python :: 3.9
Classifier: Programming Language :: Python :: 3.10
